112061619_lab3/bram/bram11.v
// bram behavior code (can't be synthesis)
// 11 words
module bram11 
(
    CLK,
    WE,
    EN,
    Di,
    Do,
    A
);

    input   wire            CLK;
    input   wire    [3:0]   WE;
    input   wire            EN;
    input   wire    [31:0]  Di;
    output  wire    [31:0]  Do;
    input   wire    [11:0]   A; 

    //  11 words
	reg [31:0] RAM[0:10];
    reg [11:0] r_A;

    always @(posedge CLK) begin
        r_A <= A;
    end

    assign Do={32{EN}}&RAM[r_A>>2];

    reg [31:0] Temp_D;
    always @(posedge CLK) begin
        if(EN) begin
	    if(WE[0]) RAM[A>>2][7:0] <= Di[7:0];
            if(WE[1]) RAM[A>>2][15:8] <= Di[15:8];
            if(WE[2]) RAM[A>>2][23:16] <= Di[23:16];
            if(WE[3]) RAM[A>>2][31:24] <= Di[31:24];
        end
    end
endmodule

112061619_lab3/lab-fir/fir/rtl/fir.v
`timescale 1ns / 1ps
module fir 
#(  parameter pADDR_WIDTH = 12,
    parameter pDATA_WIDTH = 32,
    parameter Tape_Num    = 11
)
(
    output  wire                     awready,
    output  wire                     wready,
	
    input   wire                     awvalid,
    input   wire [(pADDR_WIDTH-1):0] awaddr,
    input   wire                     wvalid,
    input   wire [(pDATA_WIDTH-1):0] wdata,
//w
    output  wire                     arready,
	
    input   wire                     rready,
    input   wire                     arvalid,
    input   wire [(pADDR_WIDTH-1):0] araddr,
	
    output  wire                     rvalid,
    output  reg  [(pDATA_WIDTH-1):0] rdata,   
//R
    input   wire                     ss_tvalid, 
    input   wire [(pDATA_WIDTH-1):0] ss_tdata, 
    input   wire                     ss_tlast, 
	
    output  wire                     ss_tready, 
//slave
    input   wire                     sm_tready, 
	
    output  reg                      sm_tvalid, 
    output  wire [(pDATA_WIDTH-1):0] sm_tdata, 
    output  reg                      sm_tlast, 
//master    
	
    // bram for tap RAM
    output  wire [3:0]               tap_WE,
    output  wire                     tap_EN,
    output  wire  [(pDATA_WIDTH-1):0] tap_Di,
    output  wire  [(pADDR_WIDTH-1):0] tap_A,
    input   wire  [(pDATA_WIDTH-1):0] tap_Do,

    // bram for data RAM
    output  reg  [3:0]               data_WE,
    output  wire                     data_EN,
    output  wire [(pDATA_WIDTH-1):0] data_Di,
    output  wire [(pADDR_WIDTH-1):0] data_A,
    input   wire [(pDATA_WIDTH-1):0] data_Do,

    input   wire                     axis_clk,
    input   wire                     axis_rst_n
);

wire [(pADDR_WIDTH-1):0]addr;
wire [(pDATA_WIDTH-1):0]ap_ctrl,mul;

wire wen,awen,ren,aren;
reg [(pDATA_WIDTH-1):0]data_length;
reg [(pDATA_WIDTH-1):0]cnt;
reg [(pDATA_WIDTH-1):0]temp;
reg [(pADDR_WIDTH-1):0]mul_cnt,i_cnt,sm_cnt,offset,j_cnt;

reg ap_done;
wire ap_start;
reg ap_idle;

assign wen=(wvalid&wready)?1'b1:1'b0;
assign awen=(awvalid&awready)?1'b1:1'b0;
assign ren=(rvalid&rready)?1'b1:1'b0;
assign aren=(arvalid&arready)?1'b1:1'b0;

assign wready=(wvalid)?1'b1:1'b0;
assign awready=(awvalid)?1'b1:1'b0;

assign rvalid=((!wvalid)&(!wready))?1'b1:1'b0;
assign arready=((!wvalid)&(!wready))?1'b1:1'b0;

assign addr=(awen|aren)?(awen)?awaddr:araddr:addr;

assign tap_WE=((wen&awen)&((awaddr>=12'h20)))?4'b1111:4'b0000;
assign tap_EN=(((wen&awen)|(ren&aren))&((addr>=12'h20))|(ap_start))?1'b1:1'b0;
assign tap_Di=(wen&((awaddr>=12'h20)))?wdata:tap_Di;
assign tap_A=(tap_EN)?(!ap_start)?addr-12'h20:i_cnt:tap_A;


always@(posedge axis_clk)begin
    if(ss_tready)begin
        data_WE<=4'b1111;
    end
    else begin
        data_WE<=4'b0000;
    end
end

assign data_EN=(ss_tvalid&ss_tready|(!ss_tlast)|ap_start)?1'b1:1'b0;
assign data_Di=(data_EN)?ss_tdata:data_Di;
assign data_A=(data_EN)?(!ap_start)?12'h00:mul_cnt:12'd40;

assign ap_start=((awaddr==12'h00)&(wdata[0]==1'b1)&awen)?1'b1:1'b0;

always@(posedge axis_clk)begin
	if(wen&awen&(awaddr==12'h10))begin
		data_length<=wdata;
	end
	else begin
		data_length<=data_length;
	end
end

always@(posedge axis_clk)begin
	if(!axis_rst_n)begin
		cnt<=32'd0;
		ap_done<=1'b0;
		sm_tlast<=1'b0;
	end
	else if(cnt==32'd7200)begin
		cnt<=cnt;
		ap_done<=1'b1;
		sm_tlast<=1'b1;
	end
	else if(ap_start) begin
		cnt<=cnt+32'b1;
		ap_done<=1'b0;
		sm_tlast<=1'b0;
	end
end

always@(posedge axis_clk)begin
	if(!axis_rst_n)begin
		ap_idle<=1'b1;
	end
	else if(ap_done)begin
		ap_idle<=1'b1;
	end
	else if(ap_start)begin
		ap_idle<=1'b0;
	end
	else begin
		ap_idle<=1'b1;
	end
end

assign ap_ctrl={29'd0,ap_idle,ap_done,ap_start};


always@(*)begin
	if(ren&aren)begin
		if(araddr==12'h00)begin
			rdata<=ap_ctrl;
		end
		else if(araddr>=12'h20)begin
			rdata<=tap_Do;
		end
		else begin
			rdata<=rdata;
		end
	end
end

assign mul=((sm_cnt>1)&(sm_cnt<=j_cnt+12'd1))?data_Do:32'd0;

always@(posedge axis_clk)begin
	if(ap_idle|ss_tready)begin
		temp<=32'd0;
	end
	else if(ap_start)begin
		temp<=temp+mul*tap_Do;
	end
	else begin
		temp<=temp;
	end
end

assign sm_tdata=(sm_tvalid&sm_tready)?temp:sm_tdata;


always@(posedge axis_clk)begin
    if(i_cnt==12'd0|ss_tready)begin
        i_cnt<=12'h28;
    end
    else if(ap_start)begin
        i_cnt<=i_cnt-12'd4;
    end
    else begin
        i_cnt<=12'h28;
    end
end

always@(posedge axis_clk)begin
    if(~ap_start)begin
        sm_cnt<=12'd0;
        sm_tvalid<=1'b0;
    end
    else if(sm_cnt>12'd10)begin
        sm_cnt<=12'd0;
        sm_tvalid<=1'b1;
    end
    else begin
        sm_cnt<=sm_cnt+12'd1;
        sm_tvalid<=1'b0;
    end
end

assign ss_tready=(ap_start&ap_idle)|sm_tvalid;

always@(posedge axis_clk)begin
    if((~axis_rst_n)|(offset>12'd10))begin
        offset<=12'd0;
    end
    else if(ss_tready)begin
        offset<=offset+12'd1;
    end
    else begin
        offset<=offset;
    end
end

always@(posedge axis_clk)begin
    if(~ap_start)begin
        mul_cnt<=12'd28;
    end
    else if(ss_tready)begin
        mul_cnt<=12'h28-offset*4;
    end
    else if(mul_cnt<12'h28)begin
        mul_cnt<=mul_cnt+12'd4;
    end
    else begin
        mul_cnt<=12'h0;
    end
end

always@(posedge axis_clk)begin
    if(~axis_rst_n)begin
        j_cnt<=12'd0;
    end
    else if(ss_tready)begin
        j_cnt<=j_cnt+12'd1;
    end
    else if(j_cnt>12'd11)begin
        j_cnt<=j_cnt;
    end
    else begin
        j_cnt<=j_cnt;
    end
end

endmodule

112061619_lab3/lab-fir/fir/tb/fir_tb.v
`timescale 1ns / 1ps
//////////////////////////////////////////////////////////////////////////////////
// Company: 
// Engineer: 
// 
// Create Date: 08/20/2023 10:38:55 AM
// Design Name: 
// Module Name: fir_tb
// Project Name: 
// Target Devices: 
// Tool Versions: 
// Description: 
// 
// Dependencies: 
// 
// Revision:
// Revision 0.01 - File Created
// Additional Comments:
// 
//////////////////////////////////////////////////////////////////////////////////


module fir_tb
#(  parameter pADDR_WIDTH = 12,
    parameter pDATA_WIDTH = 32,
    parameter Tape_Num    = 11,
    parameter Data_Num    = 600
)();
    wire                        awready;
    wire                        wready;
    reg                         awvalid;
    reg   [(pADDR_WIDTH-1): 0]  awaddr;
    reg                         wvalid;
    reg signed [(pDATA_WIDTH-1) : 0] wdata;
    wire                        arready;
    reg                         rready;
    reg                         arvalid;
    reg         [(pADDR_WIDTH-1): 0] araddr;
    wire                        rvalid;
    wire signed [(pDATA_WIDTH-1): 0] rdata;
    reg                         ss_tvalid;
    reg signed [(pDATA_WIDTH-1) : 0] ss_tdata;
    reg                         ss_tlast;
    wire                        ss_tready;
    reg                         sm_tready;
    wire                        sm_tvalid;
    wire signed [(pDATA_WIDTH-1) : 0] sm_tdata;
    wire                        sm_tlast;
    reg                         axis_clk;
    reg                         axis_rst_n;


// ram for tap
    wire [3:0]               tap_WE;
    wire                     tap_EN;
    wire [(pDATA_WIDTH-1):0] tap_Di;
    wire [(pADDR_WIDTH-1):0] tap_A;
    wire [(pDATA_WIDTH-1):0] tap_Do;

// ram for data RAM
    wire [3:0]               data_WE;
    wire                     data_EN;
    wire [(pDATA_WIDTH-1):0] data_Di;
    wire [(pADDR_WIDTH-1):0] data_A;
    wire [(pDATA_WIDTH-1):0] data_Do;



    fir fir_DUT(
        .awready(awready),
        .wready(wready),
        .awvalid(awvalid),
        .awaddr(awaddr),
        .wvalid(wvalid),
        .wdata(wdata),
        .arready(arready),
        .rready(rready),
        .arvalid(arvalid),
        .araddr(araddr),
        .rvalid(rvalid),
        .rdata(rdata),
        .ss_tvalid(ss_tvalid),
        .ss_tdata(ss_tdata),
        .ss_tlast(ss_tlast),
        .ss_tready(ss_tready),
        .sm_tready(sm_tready),
        .sm_tvalid(sm_tvalid),
        .sm_tdata(sm_tdata),
        .sm_tlast(sm_tlast),

        // ram for tap
        .tap_WE(tap_WE),
        .tap_EN(tap_EN),
        .tap_Di(tap_Di),
        .tap_A(tap_A),
        .tap_Do(tap_Do),

        // ram for data
        .data_WE(data_WE),
        .data_EN(data_EN),
        .data_Di(data_Di),
        .data_A(data_A),
        .data_Do(data_Do),

        .axis_clk(axis_clk),
        .axis_rst_n(axis_rst_n)
        );
    
    // RAM for tap
    bram11 tap_RAM (
        .CLK(axis_clk),
        .WE(tap_WE),
        .EN(tap_EN),
        .Di(tap_Di),
        .A(tap_A),
        .Do(tap_Do)
    );

    // RAM for data: choose bram11 or bram12
    bram11 data_RAM(
        .CLK(axis_clk),
        .WE(data_WE),
        .EN(data_EN),
        .Di(data_Di),
        .A(data_A),
        .Do(data_Do)
    );



    reg signed [(pDATA_WIDTH-1):0] Din_list[0:(Data_Num-1)];
    reg signed [(pDATA_WIDTH-1):0] golden_list[0:(Data_Num-1)];
    reg error_coef;

    initial begin
        $dumpfile("fir.vcd");
        $dumpvars();
    end


    initial begin
        axis_clk = 0;
        forever begin
            #5 axis_clk = (~axis_clk);
        end
    end

    initial begin
        axis_rst_n = 0;
        @(posedge axis_clk); @(posedge axis_clk);
        axis_rst_n = 1;
    end

    reg [31:0]  data_length;
    integer Din, golden, input_data, golden_data, m;
    initial begin
        data_length = 0;
        Din = $fopen("./samples_triangular_wave.dat","r");
        golden = $fopen("./out_gold.dat","r");
        for(m=0;m<Data_Num;m=m+1) begin
            input_data = $fscanf(Din,"%d", Din_list[m]);
            golden_data = $fscanf(golden,"%d", golden_list[m]);
            data_length = data_length + 1;
        end
    end

    integer i;
    initial begin
        $display("------------Start simulation-----------");
        ss_tvalid = 0;
        $display("----Start the data input(AXI-Stream)----");
		@(posedge axis_clk);
		for(i=0;i<(data_length-1);i=i+1) begin
			ss_tlast = 0; ss(Din_list[i]);
		end
        ss_tlast = 1; ss(Din_list[(Data_Num-1)]);
		@(posedge axis_clk);
		ss_tlast=0;
        $display("------End the data input(AXI-Stream)------");
    end

    integer k;
    reg error;
    reg status_error;
    initial begin
        error = 0; status_error = 0;
        sm_tready = 1;
        wait (sm_tvalid);
        for(k=0;k < data_length;k=k+1) begin
            sm(golden_list[k],k);
        end
        config_read_check(12'h00, 32'h02, 32'h0000_0002); // check ap_done = 1 (0x00 [bit 1])
        config_read_check(12'h00, 32'h04, 32'h0000_0004); // check ap_idle = 1 (0x00 [bit 2])
        if (error == 0 & error_coef == 0) begin
            $display("---------------------------------------------");
            $display("-----------Congratulations! Pass-------------");
        end
        else begin
            $display("--------Simulation Failed---------");
        end
        $finish;
    end

    // Prevent hang
    integer timeout = (1000000);
    initial begin
        while(timeout > 0) begin
            @(posedge axis_clk);
            timeout = timeout - 1;
        end
        $display($time, "Simualtion Hang ....");
        $finish;
    end


    reg signed [31:0] coef[0:10]; // fill in coef 
    initial begin
        coef[0]  =  32'd0;
        coef[1]  = -32'd10;
        coef[2]  = -32'd9;
        coef[3]  =  32'd23;
        coef[4]  =  32'd56;
        coef[5]  =  32'd63;
        coef[6]  =  32'd56;
        coef[7]  =  32'd23;
        coef[8]  = -32'd9;
        coef[9]  = -32'd10;
        coef[10] =  32'd0;
    end


    initial begin
        error_coef = 0;
		@(posedge axis_clk);arvalid <= 0;araddr <= 0;
        $display("----Start the coefficient input(AXI-lite)----");
        @(posedge axis_clk);
        config_write(12'h10, data_length);
        for(k=0; k< Tape_Num; k=k+1) begin
            config_write(12'h20+k*4, coef[k]);
        end
		@(posedge axis_clk)
        awvalid <= 0; wvalid <= 0;
        // read-back and check
        $display(" Check Coefficient ...");
		arvalid <= 0;
        for(k=0; k < Tape_Num; k=k+1) begin
            config_read_check(12'h20+k*4, coef[k], 32'hffffffff);
        end
        arvalid <= 0;
        $display(" Tape programming done ...");
        $display(" Start FIR");
        @(posedge axis_clk) config_write(12'h00, 32'h0000_0001);    // ap_start = 1
		@(posedge axis_clk) wvalid<=1'b0;
		config_read_check(12'h00, 32'h01, 32'h0000_0001);
        $display("----End the coefficient input(AXI-lite)----");
    end

    task config_write;
        input [11:0]    addr;
        input [31:0]    data;
        begin
	
			@(posedge axis_clk);
            awvalid <= 1; awaddr <= addr;
            wvalid  <= 1; wdata <= data;
            @(posedge axis_clk);
            while (!wready) @(posedge axis_clk);
        end
    endtask

    task config_read_check;
        input [11:0]        addr;
        input signed [31:0] exp_data;
        input [31:0]        mask;
        begin

            @(posedge axis_clk);
            arvalid <= 1; araddr <= addr;
            rready <= 1;
            @(posedge axis_clk);
            while (!rvalid) @(posedge axis_clk);
            @(posedge axis_clk);
            if( (rdata & mask) != (exp_data & mask)) begin
                $display("ERROR: exp = %d, rdata = %d", exp_data, rdata);
                error_coef <= 1;
            end else begin
                $display("OK: exp = %d, rdata = %d", exp_data, rdata);
            end
        end
    endtask



    task ss;
        input  signed [31:0] in1;
        begin
            ss_tvalid <= 1;
            ss_tdata  <= in1;
			@(posedge axis_clk);
            while (!(ss_tready&rvalid&rready&(rdata[0]==1'b1)&(araddr==12'h0)&sm_tvalid)) begin
                @(posedge axis_clk);
            end
        end
    endtask

    task sm;
        input  signed [31:0] in2; // golden data
        input         [31:0] pcnt; // pattern count
        begin
            sm_tready <= 1;
            @(posedge axis_clk);
            wait(sm_tvalid);
            while(!sm_tvalid) @(posedge axis_clk);
            if (sm_tdata != in2) begin
                $display("[ERROR] [Pattern %d] Golden answer: %d, Your answer: %d", pcnt, in2, sm_tdata);
                error <= 1;
            end
            else begin
                $display("[PASS] [Pattern %d] Golden answer: %d, Your answer: %d", pcnt, in2, sm_tdata);
            end
            @(posedge axis_clk);
        end
    endtask
endmodule

112061619_lab3/lab-fir/project_1/project_1.sim/sim_1/behav/xsim/fir.vcd
$date
   Wed Oct 11 09:36:01 2023
$end
$version
  2022.1
$end
$timescale
  1ps
$end
$scope module fir_tb $end
$var wire 1 ! awready $end
$var wire 1 " wready $end
$var reg 1 # awvalid $end
$var reg 12 $ awaddr [11:0] $end
$var reg 1 % wvalid $end
$var reg 32 & wdata [31:0] $end
$var wire 1 ' arready $end
$var reg 1 ( rready $end
$var reg 1 ) arvalid $end
$var reg 12 * araddr [11:0] $end
$var wire 1 + rvalid $end
$var wire 32 , rdata [31:0] $end
$var reg 1 - ss_tvalid $end
$var reg 32 . ss_tdata [31:0] $end
$var reg 1 / ss_tlast $end
$var wire 1 0 ss_tready $end
$var reg 1 1 sm_tready $end
$var wire 1 2 sm_tvalid $end
$var wire 32 3 sm_tdata [31:0] $end
$var wire 1 4 sm_tlast $end
$var reg 1 5 axis_clk $end
$var reg 1 6 axis_rst_n $end
$var wire 4 7 tap_WE [3:0] $end
$var wire 1 8 tap_EN $end
$var wire 32 9 tap_Di [31:0] $end
$var wire 12 : tap_A [11:0] $end
$var wire 32 ; tap_Do [31:0] $end
$var wire 4 < data_WE [3:0] $end
$var wire 1 = data_EN $end
$var wire 32 > data_Di [31:0] $end
$var wire 12 ? data_A [11:0] $end
$var wire 32 @ data_Do [31:0] $end
$var reg 1 A error_coef $end
$var reg 32 B data_length [31:0] $end
$var integer 32 C Din [31:0] $end
$var integer 32 D golden [31:0] $end
$var integer 32 E input_data [31:0] $end
$var integer 32 F golden_data [31:0] $end
$var integer 32 G m [31:0] $end
$var integer 32 H i [31:0] $end
$var integer 32 I k [31:0] $end
$var reg 1 J error $end
$var reg 1 K status_error $end
$var integer 32 L timeout [31:0] $end
$scope module fir_DUT $end
$var wire 1 ! awready $end
$var wire 1 " wready $end
$var wire 1 M awvalid $end
$var wire 12 N awaddr [11:0] $end
$var wire 1 O wvalid $end
$var wire 32 P wdata [31:0] $end
$var wire 1 ' arready $end
$var wire 1 Q rready $end
$var wire 1 R arvalid $end
$var wire 12 S araddr [11:0] $end
$var wire 1 + rvalid $end
$var reg 32 T rdata [31:0] $end
$var wire 1 U ss_tvalid $end
$var wire 32 V ss_tdata [31:0] $end
$var wire 1 W ss_tlast $end
$var wire 1 0 ss_tready $end
$var wire 1 X sm_tready $end
$var reg 1 Y sm_tvalid $end
$var wire 32 3 sm_tdata [31:0] $end
$var reg 1 Z sm_tlast $end
$var wire 4 7 tap_WE [3:0] $end
$var wire 1 8 tap_EN $end
$var wire 32 9 tap_Di [31:0] $end
$var wire 12 : tap_A [11:0] $end
$var wire 32 ; tap_Do [31:0] $end
$var reg 4 [ data_WE [3:0] $end
$var wire 1 = data_EN $end
$var wire 32 > data_Di [31:0] $end
$var wire 12 ? data_A [11:0] $end
$var wire 32 @ data_Do [31:0] $end
$var wire 1 \ axis_clk $end
$var wire 1 ] axis_rst_n $end
$var wire 12 ^ addr [11:0] $end
$var wire 32 _ ap_ctrl [31:0] $end
$var wire 32 ` mul [31:0] $end
$var wire 1 a wen $end
$var wire 1 b awen $end
$var wire 1 c ren $end
$var wire 1 d aren $end
$var reg 32 e data_length [31:0] $end
$var reg 32 f cnt [31:0] $end
$var reg 32 g temp [31:0] $end
$var reg 12 h mul_cnt [11:0] $end
$var reg 12 i i_cnt [11:0] $end
$var reg 12 j sm_cnt [11:0] $end
$var reg 12 k offset [11:0] $end
$var reg 12 l j_cnt [11:0] $end
$var reg 1 m ap_done $end
$var wire 1 n ap_start $end
$var reg 1 o ap_idle $end
$upscope $end
$scope module tap_RAM $end
$var wire 1 p CLK $end
$var wire 4 7 WE [3:0] $end
$var wire 1 8 EN $end
$var wire 32 9 Di [31:0] $end
$var wire 32 ; Do [31:0] $end
$var wire 12 : A [11:0] $end
$var reg 12 q r_A [11:0] $end
$var reg 32 r Temp_D [31:0] $end
$upscope $end
$scope module data_RAM $end
$var wire 1 s CLK $end
$var wire 4 < WE [3:0] $end
$var wire 1 = EN $end
$var wire 32 > Di [31:0] $end
$var wire 32 @ Do [31:0] $end
$var wire 12 ? A [11:0] $end
$var reg 12 t r_A [11:0] $end
$var reg 32 u Temp_D [31:0] $end
$upscope $end
$scope task config_write $end
$var reg 12 v addr [11:0] $end
$var reg 32 w data [31:0] $end
$upscope $end
$scope task config_read_check $end
$var reg 12 x addr [11:0] $end
$var reg 32 y exp_data [31:0] $end
$var reg 32 z mask [31:0] $end
$upscope $end
$scope task ss $end
$var reg 32 { in1 [31:0] $end
$upscope $end
$scope task sm $end
$var reg 32 | in2 [31:0] $end
$var reg 32 } pcnt [31:0] $end
$upscope $end
$upscope $end
$enddefinitions $end
#0
$dumpvars
x!
x"
x#
bx $
x%
bx &
x'
x(
x)
bx *
x+
bx ,
0-
bx .
x/
x0
11
x2
bx 3
x4
05
06
bx 7
x8
bx 9
bx :
bx ;
bx <
x=
bx >
bx ?
bx @
0A
b1001011000 B
b11111111111111111011000111100000 C
b11111111111111111011000111100001 D
b1 E
b1 F
b1001011000 G
bx H
bx I
0J
0K
b11110100001001000000 L
xM
bx N
xO
bx P
xQ
xR
bx S
bx T
0U
bx V
xW
1X
xY
xZ
bx [
0\
0]
bx ^
b0xxx _
bx `
xa
xb
xc
xd
bx e
bx f
bx g
bx h
bx i
bx j
bx k
bx l
xm
xn
xo
0p
bx q
bx r
0s
bx t
bx u
bx v
bx w
bx x
bx y
bx z
bx {
bx |
bx }
$end
#5000
0)
b0 *
1-
b1 .
0/
x0
02
bx 3
04
15
x8
bx :
b0 <
1=
b1 >
b0 ?
bx @
b0 H
b11110100001000111111 L
0R
b0 S
1U
b1 V
0W
0Y
0Z
b0 [
1\
bx ^
b10x _
bx `
0d
bx e
b0 f
bx g
b0 h
b101000 i
bx j
b0 k
b0 l
0m
1o
1p
bx q
1s
bx t
b1 {
#10000
05
0\
0p
0s
#15000
bx 3
15
16
b0x00 ?
bx @
b11110100001000111110 L
0Y
b0 [
1\
1]
bx e
b0 g
b100 h
b101000 i
bx j
b0 k
b0 l
1o
1p
bx q
1s
b0 t
b10000 v
b1001011000 w
#20000
05
0\
0p
0s
#25000
1!
1"
1#
b10000 $
1%
b1001011000 &
0'
0+
00
15
b0 7
08
bx 9
bx :
b0 ;
1=
b0 ?
bx @
b11110100001000111101 L
1M
b10000 N
1O
b1001011000 P
0Y
b0 [
1\
b10000 ^
b100 _
1a
1b
0c
0d
bx e
b0 g
b1000 h
b101000 i
bx j
b0 k
b0 l
0n
1o
1p
bx q
1s
b0x00 t
#30000
05
0\
0p
0s
#35000
15
b0 ?
bx @
b0 I
b11110100001000111100 L
0Y
b0 [
1\
b0 `
b1001011000 e
b0 g
b11100 h
b101000 i
b0 j
b0 k
b0 l
1o
1p
bx q
1s
b0 t
b100000 v
b0 w
#40000
05
0\
0p
0s
#45000
1#
b100000 $
1%
b0 &
15
b1111 7
18
b0 9
b0 :
bx ;
b11110100001000111011 L
b100000 N
b0 P
0Y
b0 [
1\
b100000 ^
b1001011000 e
b0 g
b11100 h
b101000 i
b0 j
b0 k
b0 l
0n
1o
1p
bx q
1s
b0 t
#50000
05
0\
0p
0s
#55000
15
b0 ;
b1 I
b11110100001000111010 L
0Y
b0 [
1\
b1001011000 e
b0 g
b11100 h
b101000 i
b0 j
b0 k
b0 l
1o
1p
b0 q
1s
b0 t
b100100 v
b11111111111111111111111111110110 w
#60000
05
0\
0p
0s
#65000
1#
b100100 $
1%
b11111111111111111111111111110110 &
15
b1111 7
18
b11111111111111111111111111110110 9
b100 :
b11110100001000111001 L
b100100 N
b11111111111111111111111111110110 P
0Y
b0 [
1\
b100100 ^
b1001011000 e
b0 g
b11100 h
b101000 i
b0 j
b0 k
b0 l
0n
1o
1p
b0 q
1s
b0 t
#70000
05
0\
0p
0s
#75000
15
b11111111111111111111111111110110 ;
b10 I
b11110100001000111000 L
0Y
b0 [
1\
b1001011000 e
b0 g
b11100 h
b101000 i
b0 j
b0 k
b0 l
1o
1p
b100 q
1s
b0 t
b101000 v
b11111111111111111111111111110111 w
#80000
05
0\
0p
0s
#85000
1#
b101000 $
1%
b11111111111111111111111111110111 &
15
b1111 7
18
b11111111111111111111111111110111 9
b1000 :
b11110100001000110111 L
b101000 N
b11111111111111111111111111110111 P
0Y
b0 [
1\
b101000 ^
b1001011000 e
b0 g
b11100 h
b101000 i
b0 j
b0 k
b0 l
0n
1o
1p
b100 q
1s
b0 t
#90000
05
0\
0p
0s
#95000
15
b11111111111111111111111111110111 ;
b11 I
b11110100001000110110 L
0Y
b0 [
1\
b1001011000 e
b0 g
b11100 h
b101000 i
b0 j
b0 k
b0 l
1o
1p
b1000 q
1s
b0 t
b101100 v
b10111 w
#100000
05
0\
0p
0s
#105000
1#
b101100 $
1%
b10111 &
15
b1111 7
18
b10111 9
b1100 :
b11110100001000110101 L
b101100 N
b10111 P
0Y
b0 [
1\
b101100 ^
b1001011000 e
b0 g
b11100 h
b101000 i
b0 j
b0 k
b0 l
0n
1o
1p
b1000 q
1s
b0 t
#110000
05
0\
0p
0s
#115000
15
b10111 ;
b100 I
b11110100001000110100 L
0Y
b0 [
1\
b1001011000 e
b0 g
b11100 h
b101000 i
b0 j
b0 k
b0 l
1o
1p
b1100 q
1s
b0 t
b110000 v
b111000 w
#120000
05
0\
0p
0s
#125000
1#
b110000 $
1%
b111000 &
15
b1111 7
18
b111000 9
b10000 :
b11110100001000110011 L
b110000 N
b111000 P
0Y
b0 [
1\
b110000 ^
b1001011000 e
b0 g
b11100 h
b101000 i
b0 j
b0 k
b0 l
0n
1o
1p
b1100 q
1s
b0 t
#130000
05
0\
0p
0s
#135000
15
b111000 ;
b101 I
b11110100001000110010 L
0Y
b0 [
1\
b1001011000 e
b0 g
b11100 h
b101000 i
b0 j
b0 k
b0 l
1o
1p
b10000 q
1s
b0 t
b110100 v
b111111 w
#140000
05
0\
0p
0s
#145000
1#
b110100 $
1%
b111111 &
15
b1111 7
18
b111111 9
b10100 :
b11110100001000110001 L
b110100 N
b111111 P
0Y
b0 [
1\
b110100 ^
b1001011000 e
b0 g
b11100 h
b101000 i
b0 j
b0 k
b0 l
0n
1o
1p
b10000 q
1s
b0 t
#150000
05
0\
0p
0s
#155000
15
b111111 ;
b110 I
b11110100001000110000 L
0Y
b0 [
1\
b1001011000 e
b0 g
b11100 h
b101000 i
b0 j
b0 k
b0 l
1o
1p
b10100 q
1s
b0 t
b111000 v
b111000 w
#160000
05
0\
0p
0s
#165000
1#
b111000 $
1%
b111000 &
15
b1111 7
18
b111000 9
b11000 :
b11110100001000101111 L
b111000 N
b111000 P
0Y
b0 [
1\
b111000 ^
b1001011000 e
b0 g
b11100 h
b101000 i
b0 j
b0 k
b0 l
0n
1o
1p
b10100 q
1s
b0 t
#170000
05
0\
0p
0s
#175000
15
b111000 ;
b111 I
b11110100001000101110 L
0Y
b0 [
1\
b1001011000 e
b0 g
b11100 h
b101000 i
b0 j
b0 k
b0 l
1o
1p
b11000 q
1s
b0 t
b111100 v
b10111 w
#180000
05
0\
0p
0s
#185000
1#
b111100 $
1%
b10111 &
15
b1111 7
18
b10111 9
b11100 :
b11110100001000101101 L
b111100 N
b10111 P
0Y
b0 [
1\
b111100 ^
b1001011000 e
b0 g
b11100 h
b101000 i
b0 j
b0 k
b0 l
0n
1o
1p
b11000 q
1s
b0 t
#190000
05
0\
0p
0s
#195000
15
b10111 ;
b1000 I
b11110100001000101100 L
0Y
b0 [
1\
b1001011000 e
b0 g
b11100 h
b101000 i
b0 j
b0 k
b0 l
1o
1p
b11100 q
1s
b0 t
b1000000 v
b11111111111111111111111111110111 w
#200000
05
0\
0p
0s
#205000
1#
b1000000 $
1%
b11111111111111111111111111110111 &
15
b1111 7
18
b11111111111111111111111111110111 9
b100000 :
b11110100001000101011 L
b1000000 N
b11111111111111111111111111110111 P
0Y
b0 [
1\
b1000000 ^
b1001011000 e
b0 g
b11100 h
b101000 i
b0 j
b0 k
b0 l
0n
1o
1p
b11100 q
1s
b0 t
#210000
05
0\
0p
0s
#215000
15
b11111111111111111111111111110111 ;
b1001 I
b11110100001000101010 L
0Y
b0 [
1\
b1001011000 e
b0 g
b11100 h
b101000 i
b0 j
b0 k
b0 l
1o
1p
b100000 q
1s
b0 t
b1000100 v
b11111111111111111111111111110110 w
#220000
05
0\
0p
0s
#225000
1#
b1000100 $
1%
b11111111111111111111111111110110 &
15
b1111 7
18
b11111111111111111111111111110110 9
b100100 :
b11110100001000101001 L
b1000100 N
b11111111111111111111111111110110 P
0Y
b0 [
1\
b1000100 ^
b1001011000 e
b0 g
b11100 h
b101000 i
b0 j
b0 k
b0 l
0n
1o
1p
b100000 q
1s
b0 t
#230000
05
0\
0p
0s
#235000
15
b11111111111111111111111111110110 ;
b1010 I
b11110100001000101000 L
0Y
b0 [
1\
b1001011000 e
b0 g
b11100 h
b101000 i
b0 j
b0 k
b0 l
1o
1p
b100100 q
1s
b0 t
b1001000 v
b0 w
#240000
05
0\
0p
0s
#245000
1#
b1001000 $
1%
b0 &
15
b1111 7
18
b0 9
b101000 :
b11110100001000100111 L
b1001000 N
b0 P
0Y
b0 [
1\
b1001000 ^
b1001011000 e
b0 g
b11100 h
b101000 i
b0 j
b0 k
b0 l
0n
1o
1p
b100100 q
1s
b0 t
#250000
05
0\
0p
0s
#255000
15
b0 ;
b1011 I
b11110100001000100110 L
0Y
b0 [
1\
b1001011000 e
b0 g
b11100 h
b101000 i
b0 j
b0 k
b0 l
1o
1p
b101000 q
1s
b0 t
#260000
05
0\
0p
0s
#265000
0!
0"
0#
0%
1'
0)
1+
15
b0 7
08
b0 9
b101000 :
b0 ;
b0 I
b11110100001000100101 L
0M
0O
0Y
b0 [
1\
b1001000 ^
0a
0b
xc
0d
b1001011000 e
b0 g
b11100 h
b101000 i
b0 j
b0 k
b0 l
0n
1o
1p
b101000 q
1s
b0 t
b100000 x
b0 y
b11111111111111111111111111111111 z
#270000
05
0\
0p
0s
#275000
1(
1)
b100000 *
b0 ,
15
18
b0 :
b0 ;
b11110100001000100100 L
1Q
1R
b100000 S
b0 T
0Y
b0 [
1\
b100000 ^
1c
1d
b1001011000 e
b0 g
b11100 h
b101000 i
b0 j
b0 k
b0 l
1o
1p
b101000 q
1s
b0 t
#280000
05
0\
0p
0s
#285000
15
b0 ;
b11110100001000100011 L
0Y
b0 [
1\
b1001011000 e
b0 g
b11100 h
b101000 i
b0 j
b0 k
b0 l
1o
1p
b0 q
1s
b0 t
#290000
05
0\
0p
0s
#295000
15
b1 I
b11110100001000100010 L
0Y
b0 [
1\
b1001011000 e
b0 g
b11100 h
b101000 i
b0 j
b0 k
b0 l
1o
1p
b0 q
1s
b0 t
b100100 x
b11111111111111111111111111110110 y
b11111111111111111111111111111111 z
#300000
05
0\
0p
0s
